mcp2221/__init__.py
mcp2221/enums.py
mcp2221/exceptions.py
tests/__init__.py
tests/comm.py
tests/common.py
tests/gpio.py
tests/i2c.py
tests/memory.py
tests/misc.py
tests/settings_flash.py
tests/settings_sram.py
tests/status.py
pymcp2221-1.0.12.dist-info/LICENSE
pymcp2221-1.0.12.dist-info/METADATA
pymcp2221-1.0.12.dist-info/WHEEL
pymcp2221-1.0.12.dist-info/top_level.txt
pymcp2221-1.0.12.dist-info/RECORD
