Metadata-Version: 2.1
Name: pymcp2221
Version: 1.0.12
Summary: Python driver for the Microchip MCP2221/MCP2221A USB 2.0 to I2C/UART protocol converters.
Home-page: https://github.com/vpaeder/pymcp2221
Author: Vincent Paeder
Author-email: python@paeder.fi
Project-URL: Bug Tracker, https://github.com/vpaeder/pymcp2221/issues
Keywords: MCP2221,MCP2221A,Microchip
Classifier: Development Status :: 5 - Production/Stable
Classifier: Programming Language :: Python :: 3
Classifier: License :: OSI Approved :: MIT License
Classifier: Operating System :: OS Independent
Classifier: Intended Audience :: Developers
Classifier: Topic :: Communications
Classifier: Topic :: System :: Hardware :: Hardware Drivers
Classifier: Topic :: System :: Hardware :: Universal Serial Bus (USB)
Classifier: Topic :: System :: Hardware :: Universal Serial Bus (USB) :: Human Interface Device (HID)
Requires-Python: >=3.2
License-File: LICENSE
Requires-Dist: hidapi
